{"version":3,"kind":"Article","sha256":"328840809387d1cdbaa1740d5f6755ad4e5ee344b68a1ea85559a52f894413cb","slug":"diagnostics-index","location":"/diagnostics_index.md","dependencies":[],"frontmatter":{"title":"Diagnostics","description":"CUPiD-powered diagnostics and analysis for regional MOM6 ocean models. Standardized report cards, animations, and forcing diagnostics.","github":"https://github.com/CROCODILE-CESM/CrocoGallery","source_url":"https://github.com/CROCODILE-CESM/CrocoGallery/blob/main/diagnostics_index.md","edit_url":"https://github.com/CROCODILE-CESM/CrocoGallery/edit/main/diagnostics_index.md","exports":[{"format":"md","filename":"diagnostics_index.md","url":"/CrocoGallery/latest/build/diagnostics_index-439776a7fb36b00cd06a4c83e1f453c4.md"}]},"mdast":{"type":"root","children":[{"type":"block","children":[{"type":"div","class":"croco-subspace-header croco-subspace-header--diagnostics","children":[{"type":"div","class":"croco-subspace-header__icon","children":[{"type":"text","value":"📊","key":"DV8xYW6CZo"}],"key":"hiljlfcmec"},{"type":"heading","depth":2,"children":[{"type":"text","value":"Diagnostics","key":"J75HGivg5K"}],"identifier":"diagnostics","label":"Diagnostics","html_id":"diagnostics","implicit":true,"key":"s5GRsY9RLH"},{"type":"paragraph","children":[{"type":"text","value":"CUPiD-powered diagnostics and analysis for regional MOM6 ocean models. Run standardized report cards, animations, and forcing diagnostics on your model output.","key":"nvPCv6q7yA"}],"key":"rb7ExX719x"},{"type":"link","class":"cd-btn cd-btn--outline","url":"https://cupid.readthedocs.io","children":[{"type":"text","value":"CUPiD Docs ↗","key":"mn58Pbw1oQ"}],"urlSource":"https://cupid.readthedocs.io","key":"wmha2qUSeN"}],"key":"loG5t8TTT6"},{"type":"heading","depth":3,"position":{"start":{"line":16,"column":1},"end":{"line":16,"column":1}},"children":[{"type":"text","value":"What You Can Do","position":{"start":{"line":16,"column":1},"end":{"line":16,"column":1}},"key":"UyNAq7hjQv"}],"identifier":"what-you-can-do","label":"What You Can Do","html_id":"what-you-can-do","implicit":true,"key":"GeE2XDm3N6"},{"type":"div","class":"cd-features-grid","children":[{"type":"div","class":"cd-feature","children":[{"type":"div","class":"cd-feature__icon","children":[{"type":"text","value":"📋","key":"WLNLKtFe93"}],"key":"Ex1f4J6vTQ"},{"type":"heading","depth":4,"children":[{"type":"text","value":"Report Cards","key":"KO1RQxjMnp"}],"identifier":"report-cards","label":"Report Cards","html_id":"report-cards","implicit":true,"key":"BIrO7pkn9G"},{"type":"paragraph","children":[{"type":"text","value":"Standardized diagnostic report cards that summarize model performance across key oceanographic metrics.","key":"I5CYwtNbTF"}],"key":"avQazjvzAv"}],"key":"dv4Yzc5yhv"},{"type":"div","class":"cd-feature","children":[{"type":"div","class":"cd-feature__icon","children":[{"type":"text","value":"🎞️","key":"kYLOBGOA5E"}],"key":"NhAUG8F9pM"},{"type":"heading","depth":4,"children":[{"type":"text","value":"Animations","key":"J4rvOrh8VW"}],"identifier":"animations","label":"Animations","html_id":"animations","implicit":true,"key":"j2pK8dQ6MA"},{"type":"paragraph","children":[{"type":"text","value":"Generate time-series animations of model output fields to visually assess model behavior and drift.","key":"JOaqUFLR1Q"}],"key":"uhg18hNiTS"}],"key":"A4GvGejdVQ"},{"type":"div","class":"cd-feature","children":[{"type":"div","class":"cd-feature__icon","children":[{"type":"text","value":"🌬️","key":"mWJIGB3Jn4"}],"key":"tSsTbg8A8r"},{"type":"heading","depth":4,"children":[{"type":"text","value":"Forcing Diagnostics","key":"LZRGUw660x"}],"identifier":"forcing-diagnostics","label":"Forcing Diagnostics","html_id":"forcing-diagnostics","implicit":true,"key":"mar8oPLnLK"},{"type":"paragraph","children":[{"type":"text","value":"Diagnose boundary condition and atmospheric forcing quality before and after a model run.","key":"Mu3dZ9sQIc"}],"key":"HEztrGyBkb"}],"key":"ZMsvVUQivy"},{"type":"div","class":"cd-feature","children":[{"type":"div","class":"cd-feature__icon","children":[{"type":"text","value":"🔗","key":"sYhaEabRmd"}],"key":"U9ZRQcGVRT"},{"type":"heading","depth":4,"children":[{"type":"text","value":"CESM Workflow Integration","key":"TJ49EINg5I"}],"identifier":"cesm-workflow-integration","label":"CESM Workflow Integration","html_id":"cesm-workflow-integration","implicit":true,"key":"onjWJiu7mI"},{"type":"paragraph","children":[{"type":"text","value":"Run CUPiD diagnostics as part of your standard CESM post-processing workflow.","key":"KyiQBb1ppk"}],"key":"VFgpVbbHJT"}],"key":"FLv9BxQpP9"}],"key":"Crm4ayHcxM"},{"type":"heading","depth":3,"position":{"start":{"line":41,"column":1},"end":{"line":41,"column":1}},"children":[{"type":"text","value":"Explore the Notebooks","position":{"start":{"line":41,"column":1},"end":{"line":41,"column":1}},"key":"Sc0FwRq60w"}],"identifier":"explore-the-notebooks","label":"Explore the Notebooks","html_id":"explore-the-notebooks","implicit":true,"key":"taOAsD2gor"},{"type":"div","class":"cd-nav-cards","children":[{"type":"link","class":"cd-nav-card","url":"/diagnostics/cupid-intro","children":[{"type":"heading","depth":4,"children":[{"type":"text","value":"CUPiD Introduction","key":"ilpmDKCP5f"}],"identifier":"cupid-introduction","label":"CUPiD Introduction","html_id":"cupid-introduction","implicit":true,"key":"TJkQOAfFnt"},{"type":"paragraph","children":[{"type":"text","value":"Overview of CUPiD and how it fits into the regional MOM6 diagnostics workflow.","key":"FDlrFTovMN"}],"key":"Et2msBuRRF"}],"urlSource":"diagnostics/CUPiD_intro","dataUrl":"/diagnostics.cupid-intro.json","internal":true,"protocol":"file","key":"xlCb6gOSgv"},{"type":"link","class":"cd-nav-card","url":"/diagnostics/cupid-for-regional-mom6","children":[{"type":"heading","depth":4,"children":[{"type":"text","value":"CUPiD for Regional MOM6","key":"greGf4XdQT"}],"identifier":"cupid-for-regional-mom6","label":"CUPiD for Regional MOM6","html_id":"cupid-for-regional-mom6","implicit":true,"key":"GvIrjzaBB9"},{"type":"paragraph","children":[{"type":"text","value":"Applying CUPiD diagnostics specifically to regional MOM6 model output.","key":"AoM9VNZmYb"}],"key":"UcJMFiAC92"}],"urlSource":"diagnostics/CUPiD_for_regional_MOM6","dataUrl":"/diagnostics.cupid-for-regional-mom6.json","internal":true,"protocol":"file","key":"wYY4df4UIq"},{"type":"link","class":"cd-nav-card","url":"/diagnostics/cupid-in-cesm-workflow","children":[{"type":"heading","depth":4,"children":[{"type":"text","value":"CUPiD in the CESM Workflow","key":"vIL1Uh766A"}],"identifier":"cupid-in-the-cesm-workflow","label":"CUPiD in the CESM Workflow","html_id":"cupid-in-the-cesm-workflow","implicit":true,"key":"nbqVeoJivZ"},{"type":"paragraph","children":[{"type":"text","value":"Integrating CUPiD into your end-to-end CESM case post-processing pipeline.","key":"YcCrAPyjtF"}],"key":"IGy0tWVwRr"}],"urlSource":"diagnostics/CUPiD_in_CESM_Workflow","dataUrl":"/diagnostics.cupid-in-cesm-workflow.json","internal":true,"protocol":"file","key":"LjXB2ondJ2"},{"type":"link","class":"cd-nav-card","url":"/diagnostics/standalone-cupid","children":[{"type":"heading","depth":4,"children":[{"type":"text","value":"Standalone CUPiD","key":"rdx0VAx11b"}],"identifier":"standalone-cupid","label":"Standalone CUPiD","html_id":"standalone-cupid","implicit":true,"key":"x8OoGbdrAj"},{"type":"paragraph","children":[{"type":"text","value":"Running CUPiD outside of CESM for standalone MOM6 or custom configurations.","key":"IfJnsp0yD4"}],"key":"L9ouuCVvvV"}],"urlSource":"diagnostics/standalone_CUPiD","dataUrl":"/diagnostics.standalone-cupid.json","internal":true,"protocol":"file","key":"PLW3l2vUPF"},{"type":"link","class":"cd-nav-card","url":"/diagnostics/cupid-output","children":[{"type":"heading","depth":4,"children":[{"type":"text","value":"Understanding CUPiD Output","key":"Osz3GjJjzO"}],"identifier":"understanding-cupid-output","label":"Understanding CUPiD Output","html_id":"understanding-cupid-output","implicit":true,"key":"C81epe2ksM"},{"type":"paragraph","children":[{"type":"text","value":"A guide to reading and interpreting CUPiD diagnostic output files and plots.","key":"gUuVPN8WOr"}],"key":"En45X1G8Qw"}],"urlSource":"diagnostics/CUPiD_output","dataUrl":"/diagnostics.cupid-output.json","internal":true,"protocol":"file","key":"vWHfMruWHH"},{"type":"link","class":"cd-nav-card","url":"/diagnostics/contributing-to-cupid","children":[{"type":"heading","depth":4,"children":[{"type":"text","value":"Contributing to CUPiD","key":"dpGDdaOCvb"}],"identifier":"contributing-to-cupid","label":"Contributing to CUPiD","html_id":"contributing-to-cupid","implicit":true,"key":"ZUA26gFNWI"},{"type":"paragraph","children":[{"type":"text","value":"How to add new diagnostics, notebooks, or datasets to the CUPiD framework.","key":"AuBrur8Lre"}],"key":"L5VvHuLGQn"}],"urlSource":"diagnostics/contributing_to_CUPiD","dataUrl":"/diagnostics.contributing-to-cupid.json","internal":true,"protocol":"file","key":"ePH0UkBtXA"}],"key":"xlshUMIsez"}],"key":"VZKb6f5Wok"}],"key":"EOS2WO4YxK"},"references":{"cite":{"order":[],"data":{}}},"footer":{"navigation":{"prev":{"title":"Set up a rectangular regional CESM-MOM6-CICE coupled run","url":"/crocodash/use-cases/mom6-cice-antarctica","group":"Use Cases"},"next":{"title":" CUPiD Diagnostics Tutorial ","short_title":"CUPiD Diagnostics Tutorial","url":"/diagnostics/cupid-for-regional-mom6","group":"Use Cases"}}},"domain":"http://localhost:3000"}