{"version":3,"kind":"Notebook","sha256":"c62fd169fde83d3a880a02af2b112af7a94697e8a714544bc15f9470d2483f61","slug":"notebooks.projects.tutorial1-mom6-cl-comparison","location":"/notebooks/projects/tutorial1_MOM6-CL-comparison.ipynb","dependencies":[],"frontmatter":{"title":"Tutorial 1: Model-Observation comparison with MOM6 and CrocoLake","content_includes_title":false,"github":"https://github.com/CROCODILE-CESM/CrocoGallery","numbering":{"title":{"offset":2}},"source_url":"https://github.com/CROCODILE-CESM/CrocoGallery/blob/main/gallery/notebooks/projects/tutorial1_MOM6-CL-comparison.ipynb","edit_url":"https://github.com/CROCODILE-CESM/CrocoGallery/edit/main/gallery/notebooks/projects/tutorial1_MOM6-CL-comparison.ipynb","exports":[{"format":"ipynb","filename":"tutorial1_MOM6-CL-comparison.ipynb","url":"/CrocoGallery/pr-33/build/tutorial1_MOM6-CL-co-14e1efaf096baba21c315830448be487.ipynb"}]},"widgets":{},"mdast":{"type":"root","children":[{"type":"block","kind":"notebook-content","children":[{"type":"paragraph","position":{"start":{"line":3,"column":1},"end":{"line":3,"column":1}},"children":[{"type":"text","value":"The goal of this tutorial is to get familiar with the basics of using CrocoCamp to interpolate MOM6 output onto the space of observations stored in CrocoLake. For this tutorial we will use output from a MOM6 run already stored on NCAR’s HPC system, and CrocoLake observation files already in obs_sequence format and also stored on NCAR’s HPC system.","position":{"start":{"line":3,"column":1},"end":{"line":3,"column":1}},"key":"oAiBVXN6AX"}],"key":"pPCqIjCTtI"},{"type":"heading","depth":3,"position":{"start":{"line":5,"column":1},"end":{"line":5,"column":1}},"children":[{"type":"text","value":"Installing CrocoCamp","position":{"start":{"line":5,"column":1},"end":{"line":5,"column":1}},"key":"pCu8O9zU9V"}],"identifier":"installing-crococamp","label":"Installing CrocoCamp","html_id":"installing-crococamp","implicit":true,"key":"nITYOP2Vgb"},{"type":"paragraph","position":{"start":{"line":7,"column":1},"end":{"line":7,"column":1}},"children":[{"type":"text","value":"If you don’t have CrocoCamp set up yet, ","position":{"start":{"line":7,"column":1},"end":{"line":7,"column":1}},"key":"PkRwPs6fIE"},{"type":"link","url":"https://github.com/CROCODILE-CESM/CrocoCamp/tree/2025-Crocodile-Workshop","position":{"start":{"line":7,"column":1},"end":{"line":7,"column":1}},"children":[{"type":"text","value":"here","position":{"start":{"line":7,"column":1},"end":{"line":7,"column":1}},"key":"mqRBvqOoyj"}],"urlSource":"https://github.com/CROCODILE-CESM/CrocoCamp/tree/2025-Crocodile-Workshop","error":true,"key":"y8mYHMZepA"},{"type":"text","value":" are the instructions to install it on NCAR’s HPC. If you have any issues or need to install it on a different machine, please contact ","position":{"start":{"line":7,"column":1},"end":{"line":7,"column":1}},"key":"RImxKZ2jlb"},{"type":"link","url":"mailto:enrico.milanese@whoi.edu","position":{"start":{"line":7,"column":1},"end":{"line":7,"column":1}},"children":[{"type":"text","value":"enrico​.milanese@whoi​.edu","position":{"start":{"line":7,"column":1},"end":{"line":7,"column":1}},"key":"HT72pfj6mZ"}],"urlSource":"mailto:enrico.milanese@whoi.edu","key":"VbUTyqnDcV"},{"type":"text","value":".","position":{"start":{"line":7,"column":1},"end":{"line":7,"column":1}},"key":"InEGmtYsLZ"}],"key":"lpqRI4bNde"}],"key":"rYA6v9v17t"},{"type":"block","kind":"notebook-content","children":[{"type":"heading","depth":2,"position":{"start":{"line":1,"column":1},"end":{"line":1,"column":1}},"children":[{"type":"text","value":"Running the workflow","position":{"start":{"line":1,"column":1},"end":{"line":1,"column":1}},"key":"JNmM4cfwBK"}],"identifier":"running-the-workflow","label":"Running the workflow","html_id":"running-the-workflow","implicit":true,"key":"vk2wdQhQxv"},{"type":"paragraph","position":{"start":{"line":3,"column":1},"end":{"line":3,"column":1}},"children":[{"type":"text","value":"Running the workflow to interpolate the model is quite simple: create a ","position":{"start":{"line":3,"column":1},"end":{"line":3,"column":1}},"key":"MzEFc06jho"},{"type":"inlineCode","value":"WorkflowModelObs","position":{"start":{"line":3,"column":1},"end":{"line":3,"column":1}},"key":"kp9JwDYWAF"},{"type":"text","value":" instance using a configuration file, and then call its ","position":{"start":{"line":3,"column":1},"end":{"line":3,"column":1}},"key":"o93WWZ1sdO"},{"type":"inlineCode","value":"run()","position":{"start":{"line":3,"column":1},"end":{"line":3,"column":1}},"key":"GQVxzgPJWz"},{"type":"text","value":" method. For this tutorial we will use the configuration file provided ","position":{"start":{"line":3,"column":1},"end":{"line":3,"column":1}},"key":"YhExbMAaze"},{"type":"inlineCode","value":"config_tutorial_1.yaml","position":{"start":{"line":3,"column":1},"end":{"line":3,"column":1}},"key":"SpJbUce5B1"},{"type":"text","value":" in the ","position":{"start":{"line":3,"column":1},"end":{"line":3,"column":1}},"key":"o5gbZt4YKc"},{"type":"inlineCode","value":"tutorial","position":{"start":{"line":3,"column":1},"end":{"line":3,"column":1}},"key":"j9rSTr0Fom"},{"type":"text","value":" folder. A template file to use as reference is also provided at ","position":{"start":{"line":3,"column":1},"end":{"line":3,"column":1}},"key":"ugFJXnRQck"},{"type":"inlineCode","value":"../configs/config_template.yaml","position":{"start":{"line":3,"column":1},"end":{"line":3,"column":1}},"key":"knRBtkdtBQ"},{"type":"text","value":".","position":{"start":{"line":3,"column":1},"end":{"line":3,"column":1}},"key":"wUqQF2v98t"}],"key":"Gjx4sbGDM8"},{"type":"paragraph","position":{"start":{"line":5,"column":1},"end":{"line":5,"column":1}},"children":[{"type":"text","value":"While running, CrocoCamp generates temporary input files that tell DART’s ","position":{"start":{"line":5,"column":1},"end":{"line":5,"column":1}},"key":"KylWcqmnxq"},{"type":"inlineCode","value":"perfect_model_obs","position":{"start":{"line":5,"column":1},"end":{"line":5,"column":1}},"key":"DCguD6noLO"},{"type":"text","value":" executable where to find MOM6 and CrocoLake data to perform the interpolation. You need to be running this notebook on Casper, as the configuration file points to DART’s installation on that machine.","position":{"start":{"line":5,"column":1},"end":{"line":5,"column":1}},"key":"ZSCMI8yXE5"}],"key":"eoU7fM2pw4"}],"key":"yB8hFjTShI"},{"type":"block","kind":"notebook-code","children":[{"type":"code","lang":"python","executable":true,"value":"from crococamp.workflows import WorkflowModelObs\n\n# Create and run workflow to interpolate MOM6 model onto World Ocean Database obs space\nworkflow_crocolake = WorkflowModelObs.from_config_file('config_tutorial_1.yaml')\nworkflow_crocolake.run() #use flag clear_output=True if you want to re-run it and automatically clean all previous output","key":"sa8QSVHkB5"},{"type":"outputs","id":"sICMqMQwty_xDkOLK7Bhm","children":[],"key":"UkSl4Rle4T"}],"key":"FmYmeU134a"},{"type":"block","kind":"notebook-content","children":[{"type":"heading","depth":2,"position":{"start":{"line":1,"column":1},"end":{"line":1,"column":1}},"children":[{"type":"text","value":"Displaying the interactive map","position":{"start":{"line":1,"column":1},"end":{"line":1,"column":1}},"key":"QWStZ8sqXq"}],"identifier":"displaying-the-interactive-map","label":"Displaying the interactive map","html_id":"displaying-the-interactive-map","implicit":true,"key":"JsR3DuUUn9"},{"type":"paragraph","position":{"start":{"line":3,"column":1},"end":{"line":3,"column":1}},"children":[{"type":"text","value":"CrocoCamp generates a parquet dataset that contains the values of the WOD observations, the MOM6 model data interpolated onto the observations space, and some basic statistics.","position":{"start":{"line":3,"column":1},"end":{"line":3,"column":1}},"key":"W8EdZwzeF0"}],"key":"fVnNkRA9BG"},{"type":"paragraph","position":{"start":{"line":5,"column":1},"end":{"line":5,"column":1}},"children":[{"type":"text","value":"The dataframe by default is stored to ","position":{"start":{"line":5,"column":1},"end":{"line":5,"column":1}},"key":"rtiRcZn9b5"},{"type":"inlineCode","value":"model_obs_df","position":{"start":{"line":5,"column":1},"end":{"line":5,"column":1}},"key":"y5UpkZErt2"},{"type":"text","value":" (as a dask dataframe), and CrocoCamp offers tools to access all data, only the successful interpolations, or only the failed interpolations. For now, let’s load only the interpolations that succeeded, which are ~98% of the total (see output message from previous cell):","position":{"start":{"line":5,"column":1},"end":{"line":5,"column":1}},"key":"nW3x4EVU2K"}],"key":"Fvylf4Ks3y"}],"key":"EAAcf9pwde"},{"type":"block","kind":"notebook-code","children":[{"type":"code","lang":"python","executable":true,"value":"good_model_obs_df = workflow_crocolake.get_good_model_obs_df(compute=True) # compute=True triggers the compute of the dask dataframe, returning a pandas dataframe with data loaded in memory\ngood_model_obs_df.head()                                                   # displays first 5 rows in the dataframe","key":"QVEOZv7dmr"},{"type":"outputs","id":"bjwwTGwwyHnYuSCR7gvRr","children":[],"key":"RF32OGdron"}],"key":"zSkzNOqaL7"},{"type":"block","kind":"notebook-content","children":[{"type":"paragraph","position":{"start":{"line":1,"column":1},"end":{"line":1,"column":1}},"children":[{"type":"text","value":"Loading the interactive map to explore the succesfull interpolations is as simple as importing the widget and passing the dataframe to it:","position":{"start":{"line":1,"column":1},"end":{"line":1,"column":1}},"key":"GV9CbBqxii"}],"key":"jk1CfXXXwC"}],"key":"txdP8PsOiY"},{"type":"block","kind":"notebook-code","children":[{"type":"code","lang":"python","executable":true,"value":"from crococamp.viz import InteractiveWidgetMap\n# Create an interactive map widget to visualize model-observation comparisons\n# The widget provides controls for selecting variables, observation types, and time ranges\nwidget = InteractiveWidgetMap(good_model_obs_df)\nwidget.setup()","key":"uKnk1ey5y1"},{"type":"outputs","id":"R_kTckVIglRmv5NYxzSE6","children":[],"key":"QFKbS3t7gi"}],"key":"ffjg4R3rxF"},{"type":"block","kind":"notebook-content","children":[{"type":"heading","depth":2,"position":{"start":{"line":1,"column":1},"end":{"line":1,"column":1}},"children":[{"type":"text","value":"Interpolation errors","position":{"start":{"line":1,"column":1},"end":{"line":1,"column":1}},"key":"UP5yo6WbZG"}],"identifier":"interpolation-errors","label":"Interpolation errors","html_id":"interpolation-errors","implicit":true,"key":"FDanDg37qK"},{"type":"paragraph","position":{"start":{"line":3,"column":1},"end":{"line":3,"column":1}},"children":[{"type":"text","value":"The dataframe built by CrocoCamp during ","position":{"start":{"line":3,"column":1},"end":{"line":3,"column":1}},"key":"XnzEMzkMq7"},{"type":"inlineCode","value":"WorkflowModelObs.run()","position":{"start":{"line":3,"column":1},"end":{"line":3,"column":1}},"key":"xd2vRtZTNn"},{"type":"text","value":" contains the column ","position":{"start":{"line":3,"column":1},"end":{"line":3,"column":1}},"key":"cDIJbnP5q9"},{"type":"inlineCode","value":"interpolated_model_QC","position":{"start":{"line":3,"column":1},"end":{"line":3,"column":1}},"key":"ToXbAP8rRR"},{"type":"text","value":", which stores information about the quality of the interpolation. The value is set by DART’s ","position":{"start":{"line":3,"column":1},"end":{"line":3,"column":1}},"key":"lLiI0kOamE"},{"type":"inlineCode","value":"perfect_model_obs","position":{"start":{"line":3,"column":1},"end":{"line":3,"column":1}},"key":"XUat5ryOT3"},{"type":"text","value":" program, and you can find more information about it ","position":{"start":{"line":3,"column":1},"end":{"line":3,"column":1}},"key":"WbVUYJWEzZ"},{"type":"link","url":"https://docs.dart.ucar.edu/en/stable/assimilation_code/modules/assimilation/quality_control_mod.html","position":{"start":{"line":3,"column":1},"end":{"line":3,"column":1}},"children":[{"type":"text","value":"here","position":{"start":{"line":3,"column":1},"end":{"line":3,"column":1}},"key":"isUGmJ3icy"}],"urlSource":"https://docs.dart.ucar.edu/en/stable/assimilation_code/modules/assimilation/quality_control_mod.html","key":"aMKCGWnIBF"},{"type":"text","value":" and ","position":{"start":{"line":3,"column":1},"end":{"line":3,"column":1}},"key":"xH0hrtkcx4"},{"type":"link","url":"https://github.com/NCAR/DART/blob/1ddc21f418175fab0768b572866f54a2983dbb66/models/MOM6/model_mod.f90#L119C23-L119C41","position":{"start":{"line":3,"column":1},"end":{"line":3,"column":1}},"children":[{"type":"text","value":"here","position":{"start":{"line":3,"column":1},"end":{"line":3,"column":1}},"key":"cl4dvy45xE"}],"urlSource":"https://github.com/NCAR/DART/blob/1ddc21f418175fab0768b572866f54a2983dbb66/models/MOM6/model_mod.f90#L119C23-L119C41","data":{"kind":"file","org":"NCAR","repo":"DART","reference":"1ddc21f418175fab0768b572866f54a2983dbb66","file":"models/MOM6/model_mod.f90","from":119,"raw":"https://raw.githubusercontent.com/NCAR/DART/1ddc21f418175fab0768b572866f54a2983dbb66/models/MOM6/model_mod.f90"},"internal":false,"protocol":"github","key":"o7brMp3DOq"},{"type":"text","value":". In general, for this workflow we want QC≤2, and indeed the method ","position":{"start":{"line":3,"column":1},"end":{"line":3,"column":1}},"key":"VO2EYYEgkt"},{"type":"inlineCode","value":"get_good_model_obs_df()","position":{"start":{"line":3,"column":1},"end":{"line":3,"column":1}},"key":"K2sA7mNeg7"},{"type":"text","value":" that we used earlier uses this criterion.","position":{"start":{"line":3,"column":1},"end":{"line":3,"column":1}},"key":"xAlKtZ97QK"}],"key":"VkuG8OXVbM"},{"type":"paragraph","position":{"start":{"line":5,"column":1},"end":{"line":5,"column":1}},"children":[{"type":"text","value":"Let’s now have a look at the failed interpolations by loading the data and plotting it:","position":{"start":{"line":5,"column":1},"end":{"line":5,"column":1}},"key":"VEtWSz8ZNp"}],"key":"T1yGX9RvvH"}],"key":"RU4Fbl5UmJ"},{"type":"block","kind":"notebook-code","children":[{"type":"code","lang":"python","executable":true,"value":"failed_model_obs_df = workflow_crocolake.get_failed_model_obs_df(compute=True) # compute=True triggers the compute of the dask dataframe, returning a pandas dataframe with data loaded in memory\nfailed_model_obs_df.head()                                                     # displays first 5 rows in the dataframe","key":"lhJQnzMDmo"},{"type":"outputs","id":"-n3j14EZ6YW9f4NxiBePO","children":[],"key":"cOYzgzDVDO"}],"key":"TyN2EHyoql"},{"type":"block","kind":"notebook-code","children":[{"type":"code","lang":"python","executable":true,"value":"widget_failed = InteractiveWidgetMap(good_model_obs_df)\nwidget_failed.setup()","key":"tRqIjzX73V"},{"type":"outputs","id":"lqL9w8bg4CqRC7ZFAmFqj","children":[],"key":"RqQdlMt8CK"}],"key":"z9Vu1ymQDS"},{"type":"block","kind":"notebook-content","children":[{"type":"paragraph","position":{"start":{"line":1,"column":1},"end":{"line":1,"column":1}},"children":[{"type":"text","value":"We note two things:","position":{"start":{"line":1,"column":1},"end":{"line":1,"column":1}},"key":"thiMLliKh8"}],"key":"NjZkJqKZaw"},{"type":"list","ordered":true,"start":1,"spread":false,"position":{"start":{"line":3,"column":1},"end":{"line":6,"column":1}},"children":[{"type":"listItem","spread":true,"position":{"start":{"line":3,"column":1},"end":{"line":3,"column":1}},"children":[{"type":"paragraph","children":[{"type":"text","value":"when an interpolation fails, a value of -888888 is assigned to the interpolated model;","position":{"start":{"line":3,"column":1},"end":{"line":3,"column":1}},"key":"kIxRHnloRF"}],"key":"gIuM6aKQEw"}],"key":"dDXOt08V3R"},{"type":"listItem","spread":true,"position":{"start":{"line":4,"column":1},"end":{"line":4,"column":1}},"children":[{"type":"paragraph","children":[{"type":"text","value":"from ","position":{"start":{"line":4,"column":1},"end":{"line":4,"column":1}},"key":"SBsHqeQNdn"},{"type":"inlineCode","value":"head()","position":{"start":{"line":4,"column":1},"end":{"line":4,"column":1}},"key":"hoVx7hB6gO"},{"type":"text","value":", we see values of QC greater than 1000.","position":{"start":{"line":4,"column":1},"end":{"line":4,"column":1}},"key":"cNuXDdR4dZ"}],"key":"WwKlGH6hGw"}],"key":"j1Y8G4tAwL"},{"type":"listItem","spread":true,"position":{"start":{"line":5,"column":1},"end":{"line":6,"column":1}},"children":[{"type":"paragraph","children":[{"type":"text","value":"the failed observations are close to the model boundaries (north and east) or to land (west);","position":{"start":{"line":5,"column":1},"end":{"line":5,"column":1}},"key":"vz9NvPeNFi"}],"key":"o5G5cLzktz"}],"key":"DaO2KaunrD"}],"key":"C6nbgHwyar"},{"type":"paragraph","position":{"start":{"line":7,"column":1},"end":{"line":7,"column":1}},"children":[{"type":"text","value":"The following command gives us the unique values of ","position":{"start":{"line":7,"column":1},"end":{"line":7,"column":1}},"key":"Tr60VG6MMB"},{"type":"inlineCode","value":"model_QC","position":{"start":{"line":7,"column":1},"end":{"line":7,"column":1}},"key":"ZsMTbRyKua"},{"type":"text","value":":","position":{"start":{"line":7,"column":1},"end":{"line":7,"column":1}},"key":"nFImxT4wTE"}],"key":"ElXTOHgnnA"}],"key":"HJjWVJDQqg"},{"type":"block","kind":"notebook-code","children":[{"type":"code","lang":"python","executable":true,"value":"failed_model_obs_df['interpolated_model_QC'].unique()","key":"QAv0TUj8E5"},{"type":"outputs","id":"NPvgd6Ssv5g8xEP2t5ZKx","children":[],"key":"ir8jK2O4jz"}],"key":"MYjYlJMK9Q"},{"type":"block","kind":"notebook-content","children":[{"type":"paragraph","position":{"start":{"line":1,"column":1},"end":{"line":1,"column":1}},"children":[{"type":"text","value":"We should have only values equal to 1018. Values greater than 1000 are given as 1000 + failure_code, with failure_code from ","position":{"start":{"line":1,"column":1},"end":{"line":1,"column":1}},"key":"TepPMkMw9c"},{"type":"link","url":"https://github.com/NCAR/DART/blob/1ddc21f418175fab0768b572866f54a2983dbb66/models/MOM6/model_mod.f90#L119C23-L119C41","position":{"start":{"line":1,"column":1},"end":{"line":1,"column":1}},"children":[{"type":"text","value":"here","position":{"start":{"line":1,"column":1},"end":{"line":1,"column":1}},"key":"LvhDyWDw7G"}],"urlSource":"https://github.com/NCAR/DART/blob/1ddc21f418175fab0768b572866f54a2983dbb66/models/MOM6/model_mod.f90#L119C23-L119C41","data":{"kind":"file","org":"NCAR","repo":"DART","reference":"1ddc21f418175fab0768b572866f54a2983dbb66","file":"models/MOM6/model_mod.f90","from":119,"raw":"https://raw.githubusercontent.com/NCAR/DART/1ddc21f418175fab0768b572866f54a2983dbb66/models/MOM6/model_mod.f90"},"internal":false,"protocol":"github","key":"C7rftRUD0e"},{"type":"text","value":". In this case, the QC flag 1018 indicates that one or more grid points required for the interpolation are not in the basin, so the interpolation cannot be performed. This is consistent with the visual inspection from the map, where we noticed that failed interpolations are closed to model boundary and to the sea/land border.","position":{"start":{"line":1,"column":1},"end":{"line":1,"column":1}},"key":"HmgDCJNi7q"}],"key":"UHaCovexGx"},{"type":"paragraph","position":{"start":{"line":3,"column":1},"end":{"line":3,"column":1}},"children":[{"type":"text","value":"Finally, if you want to load all the data at once, you can use the following command:","position":{"start":{"line":3,"column":1},"end":{"line":3,"column":1}},"key":"us5ePr0CRM"}],"key":"S57Div3m9q"}],"key":"Z2t6FixGIl"},{"type":"block","kind":"notebook-code","children":[{"type":"code","lang":"python","executable":true,"value":"# Load the parquet dataset generated by the workflow above\nmodel_obs_df = workflow_crocolake.get_all_model_obs_df(compute=True) # compute=True triggers the compute of the dask dataframe, returning a pandas dataframe with data loaded in memory\nmodel_obs_df.head() # displays first 5 rows in the dataframe","key":"qgacsK8fEQ"},{"type":"outputs","id":"6tEXFCavG93ABLhErF5Gp","children":[],"key":"ptaMdx1LIU"}],"key":"SPSXL7dTQk"}],"key":"u4RcBipXwW"},"references":{"cite":{"order":[],"data":{}}},"footer":{"navigation":{"prev":{"title":"Model-Observations Comparison","short_title":"Tutorials for Model-Observation Comparison","url":"/notebooks/projects/model-obs-comparison","group":"Sample Projects"},"next":{"title":"Tutorial 2: Model-Observation comparison with MOM6 and a single Argo float from CrocoLake","url":"/notebooks/projects/tutorial2-mom6-cl-comparison-float","group":"Sample Projects"}}},"domain":"http://localhost:3000"}